scriptl/__init__.py
scriptl/console.py
scriptl-0.2.dist-info/METADATA
scriptl-0.2.dist-info/WHEEL
scriptl-0.2.dist-info/top_level.txt
scriptl-0.2.dist-info/RECORD
